{
  "project_info": {
    "project_number": "721615958546",
    "project_id": "poimapvinhkhanh",
    "storage_bucket": "poimapvinhkhanh.firebasestorage.app"
  },
  "client": [
    {
      "client_info": {
        "mobilesdk_app_id": "1:721615958546:android:6932792963b77f00aadecb",
        "android_client_info": {
          "package_name": "com.companyname.poimap"
        }
      },
      "oauth_client": [],
      "api_key": [
        {
          "current_key": "AIzaSyDKIQ4F4dsD4Qt2heOX7KTvl35BttvP8Ag"
        }
      ],
      "services": {
        "appinvite_service": {
          "other_platform_oauth_client": []
        }
      }
    }
  ],
  "configuration_version": "1"
}